{
    "configNum": 2,
    "configs": {
        "configs_0": {
            "asset": "0xaf88d065e77c8cc2239327c5edb3a432268e5831",
            "bufferConfig": {
                "minimumBuffer": 5000000000,
                "maximumBuffer": 10000000000,
                "buffer": 7000000000
            }
        },
        "configs_1": {
            "asset": "0x82af49447d8a07e3bd95bd0d56f35241523fbab1",
            "bufferConfig": {
                "minimumBuffer": 2000000000000000000,
                "maximumBuffer": 4000000000000000000,
                "buffer": 3000000000000000000
            }
        }
    }
}